{
  "sections": {
    "main": {
      "type": "main-product-double-serum",
      "blocks": {
        "product_meta": {
          "type": "product_meta",
          "settings": {
            "show_vendor": false,
            "show_sku": false,
            "show_product_rating": false,
            "show_taxes_included": false,
            "product_type": "2層式美容液",
            "product_guide": "20ml（約20日分）"
          }
        },
        "cfa5e61e-eb14-406c-bb55-f7908d1a9121": {
          "type": "label",
          "settings": {
            "label": "ザラつき"
          }
        },
        "e3ed950b-bdf9-419f-aa90-caaf5445d2c2": {
          "type": "label",
          "settings": {
            "label": "肌荒れ(※1)"
          }
        },
        "81e40830-e88c-4cf6-8f61-7275a7a60b1b": {
          "type": "label",
          "settings": {
            "label": "敏感肌"
          }
        },
        "51f232e8-7b28-4d1b-b343-9111bf07e19c": {
          "type": "label",
          "settings": {
            "label": "ニキビのあと(※2)"
          }
        },
        "559a5693-87bd-49c0-9786-fcd03b14e83b": {
          "type": "label",
          "settings": {
            "label": "くもった表情"
          }
        },
        "16e4e4d1-5f82-4ba9-bda8-de9b3cabfabc": {
          "type": "title_with_text",
          "settings": {
            "heading": "<p>化粧品の「カバー力」に頼らない。<\/p><p>自立した肌を目指す美容液。<\/p>",
            "text": "<p>くもった表情やニキビのあと(※2)。<\/p><p>悩み多き大人の肌事情へアプローチする美容成分配合。化粧品に頼りがちな肌を、卒業してみませんか。<\/p><p>パラベン・鉱物油・石油界面活性剤・合成香料・合成着色料・シリコン・旧指定成分・アルコール（エタノール）不使用。<\/p>",
            "caution": "(※1) 保湿による予防 (※2) ニキビが落ち着いた後の敏感な肌のこと"
          }
        },
        "32ba579a-c0ca-40a7-b6a4-bb64bcebd816": {
          "type": "image",
          "settings": {
            "image": "shopify:\/\/shop_images\/double-serum1.jpg"
          }
        },
        "511919d2-2698-4339-aed2-e0eb592c3773": {
          "type": "product_description",
          "settings": {
          }
        },
        "share_buttons": {
          "type": "share_buttons",
          "settings": {
          }
        },
        "variant_selector": {
          "type": "variant_selector",
          "settings": {
            "selector_mode": "dropdown",
            "show_color_swatch": false,
            "show_color_carousel": false,
            "size_chart": ""
          }
        },
        "quantity_selector": {
          "type": "quantity_selector",
          "settings": {
            "show_label": false
          }
        },
        "buy_buttons": {
          "type": "buy_buttons",
          "settings": {
            "show_price_in_button": false,
            "show_payment_button": true
          }
        },
        "fdab9f1a-889d-42ad-87d1-3ffc9c24c203": {
          "type": "usage",
          "settings": {
          }
        },
        "description": {
          "type": "description",
          "settings": {
          }
        },
        "opinew-stars-plugin-product": {
          "type": "shopify:\/\/apps\/opinew-product-reviews-app\/blocks\/product-stars\/e1d8e0dc-17ff-4e4a-8a8a-1e73c8ef8676",
          "disabled": true,
          "settings": {
          }
        },
        "c75d8bb2-4caf-4fed-a264-8007351b4f56": {
          "type": "shopify:\/\/apps\/opinew-product-reviews-app\/blocks\/product-widget\/e1d8e0dc-17ff-4e4a-8a8a-1e73c8ef8676",
          "settings": {
          }
        }
      },
      "block_order": [
        "product_meta",
        "cfa5e61e-eb14-406c-bb55-f7908d1a9121",
        "e3ed950b-bdf9-419f-aa90-caaf5445d2c2",
        "81e40830-e88c-4cf6-8f61-7275a7a60b1b",
        "51f232e8-7b28-4d1b-b343-9111bf07e19c",
        "559a5693-87bd-49c0-9786-fcd03b14e83b",
        "16e4e4d1-5f82-4ba9-bda8-de9b3cabfabc",
        "32ba579a-c0ca-40a7-b6a4-bb64bcebd816",
        "511919d2-2698-4339-aed2-e0eb592c3773",
        "share_buttons",
        "variant_selector",
        "quantity_selector",
        "buy_buttons",
        "fdab9f1a-889d-42ad-87d1-3ffc9c24c203",
        "description",
        "opinew-stars-plugin-product",
        "c75d8bb2-4caf-4fed-a264-8007351b4f56"
      ],
      "settings": {
        "image_size": "large",
        "stack_images": true,
        "show_thumbnails": true,
        "enable_image_zoom": true,
        "enable_video_looping": false
      }
    },
    "164352635359c05d0d": {
      "type": "apps",
      "blocks": {
        "f0a528f9-9a42-449d-9cea-c21cfa39c9e5": {
          "type": "shopify:\/\/apps\/opinew-product-reviews-app\/blocks\/product-stars\/e1d8e0dc-17ff-4e4a-8a8a-1e73c8ef8676",
          "disabled": true,
          "settings": {
          }
        }
      },
      "block_order": [
        "f0a528f9-9a42-449d-9cea-c21cfa39c9e5"
      ],
      "settings": {
        "include_margins": true
      }
    },
    "opinew-reviews-product-page-code": {
      "type": "apps",
      "blocks": {
        "opinew-reviews-widget": {
          "type": "shopify:\/\/apps\/opinew-product-reviews-app\/blocks\/product-widget\/e1d8e0dc-17ff-4e4a-8a8a-1e73c8ef8676",
          "settings": {
          }
        }
      },
      "block_order": [
        "opinew-reviews-widget"
      ],
      "settings": {
        "include_margins": true
      }
    }
  },
  "order": [
    "main",
    "164352635359c05d0d",
    "opinew-reviews-product-page-code"
  ]
}
